SpaCell/__init__.py
SpaCell/config.py
SpaCell/count_matrix_normalization.py
SpaCell/dataset_management.py
SpaCell/image_normalization.py
SpaCell/model.py
SpaCell/spacell_classification.py
SpaCell/spacell_clustering.py
SpaCell/spacell_validation.py
SpaCell/utils.py
Spacell-1.0.1.dist-info/LICENSE
Spacell-1.0.1.dist-info/METADATA
Spacell-1.0.1.dist-info/WHEEL
Spacell-1.0.1.dist-info/top_level.txt
Spacell-1.0.1.dist-info/RECORD
